_version.py
config.py
rss_reader.py
argument_parser/__init__.py
argument_parser/arg_parser.py
content_aggregator/__init__.py
content_aggregator/rss_aggregator.py
db_manager/__init__.py
db_manager/manager.py
output_manager/__init__.py
output_manager/console_output.py
output_manager/converter.py
rss_reader_sardor_irgashev-5.0.0.dist-info/LICENSE
rss_reader_sardor_irgashev-5.0.0.dist-info/METADATA
rss_reader_sardor_irgashev-5.0.0.dist-info/WHEEL
rss_reader_sardor_irgashev-5.0.0.dist-info/entry_points.txt
rss_reader_sardor_irgashev-5.0.0.dist-info/top_level.txt
rss_reader_sardor_irgashev-5.0.0.dist-info/RECORD
