Metadata-Version: 2.1
Name: rss-reader-sardor-irgashev
Version: 5.0.0
Summary: Command-line RSS reader utility
Author: Sardor Irgashev
Author-email: irgashevsardor99@gmail.com
License: UNKNOWN
Platform: UNKNOWN
Classifier: Programming Language :: Python :: 3
Classifier: License :: OSI Approved :: MIT License
Classifier: Operating System :: OS Independent
Requires-Python: >=3.6
License-File: LICENSE
Requires-Dist: beautifulsoup4 (==4.11.1)
Requires-Dist: lxml (==4.8.0)
Requires-Dist: requests (==2.27.1)
Requires-Dist: xhtml2pdf (==0.2.7)
Requires-Dist: yattag (==1.14.0)
